oklearn/__init__.py
oklearn/measure_prediction_accuracy.py
oklearn/preprocessing.py
oklearn-0.0.1.dist-info/METADATA
oklearn-0.0.1.dist-info/WHEEL
oklearn-0.0.1.dist-info/top_level.txt
oklearn-0.0.1.dist-info/RECORD
